{
  "artifact_schema_version": 5,
  "data": {
    "candidate_ticker_count": 4137,
    "candidate_ticker_universe_sha256": "737d1552c27b4094f243bbd19479504b8b58cff3281a033d81f099666875ac7b",
    "eligible_row_count": 384985,
    "labeled_row_count": 384985,
    "panel_row_count": 10404555,
    "positive_label_rate": 0.4760990687948881,
    "positive_label_rows": 183291,
    "price_end_date": "2024-12-31T00:00:00",
    "price_start_date": "2014-10-06T00:00:00"
  },
  "debug_metadata_path": "debug_metadata.json",
  "evaluation": {
    "aggregate_metrics": {
      "brier_score": 0.25183542012766985,
      "gate_survival_rate": 0.522479924156283,
      "log_loss": 0.6970871026634601,
      "passed_trades_avg_return": -0.0002818009996234966,
      "passed_trades_hit_rate": 0.4861531514025638,
      "passed_trades_recall": 0.5062585809073417,
      "roc_auc": 0.5107693283083687,
      "total_surviving_test_rows": 176907,
      "total_test_rows": 338591
    },
    "baseline_comparisons": {
      "stage2_ranker_vs_equal_weight_signals": {
        "baseline_strategy": "equal_weight_signals",
        "hit_rate_delta": -0.0071458503496160675,
        "mean_net_return_per_trade_delta": -0.0009103304988267795,
        "primary_strategy": "stage2_ranker",
        "total_trade_count_delta": -332124
      },
      "stage2_ranker_vs_stage1_probability": {
        "baseline_strategy": "stage1_probability",
        "hit_rate_delta": 0.002305037710994773,
        "mean_daily_ndcg_for_top_3_delta": 0.02710090733296161,
        "mean_daily_ndcg_for_top_6_delta": 0.04205025250690719,
        "mean_daily_ndcg_for_top_9_delta": 0.05569437279114553,
        "mean_daily_net_return_for_top_3_delta": 0.0002959569037595509,
        "mean_daily_net_return_for_top_6_delta": -0.00045210325839678414,
        "mean_daily_net_return_for_top_9_delta": -0.0001768584094475733,
        "mean_daily_precision_for_top_3_delta": 0.0019033800315522709,
        "mean_daily_precision_for_top_6_delta": -0.0028649178053573032,
        "mean_daily_precision_for_top_9_delta": -0.004166970900471634,
        "mean_net_return_per_trade_delta": 0.0005826680712136213,
        "primary_strategy": "stage2_ranker",
        "total_trade_count_delta": -191
      }
    },
    "completed_split_count": 37,
    "skipped_split_count": 0,
    "split_stability": {
      "stage1_classifier_gate": {
        "brier_score": {
          "completed_split_count": 37,
          "max": 0.2598793544098753,
          "mean": 0.25183542012766985,
          "min": 0.2453172844119442,
          "std": 0.003238971720072728
        },
        "gate_survival_rate": {
          "completed_split_count": 37,
          "max": 0.8640308582449373,
          "mean": 0.4978781360228329,
          "min": 0.17555318581711543,
          "std": 0.18286760045294503
        },
        "log_loss": {
          "completed_split_count": 37,
          "max": 0.713744586240436,
          "mean": 0.6970871026634601,
          "min": 0.6837114158426555,
          "std": 0.006683777406435862
        },
        "passed_trades_avg_return": {
          "completed_split_count": 37,
          "max": 0.007821431489238983,
          "mean": -0.0002818009996234966,
          "min": -0.007869272770801775,
          "std": 0.003099430839676232
        },
        "passed_trades_hit_rate": {
          "completed_split_count": 37,
          "max": 0.5527086383601757,
          "mean": 0.4861531514025638,
          "min": 0.41133004926108374,
          "std": 0.033229198345428944
        },
        "passed_trades_recall": {
          "completed_split_count": 37,
          "max": 0.8664010067114094,
          "mean": 0.5062585809073417,
          "min": 0.16118800461361016,
          "std": 0.18679210216448808
        },
        "roc_auc": {
          "completed_split_count": 37,
          "max": 0.5629101396375844,
          "mean": 0.5107693283083687,
          "min": 0.4643290107900607,
          "std": 0.022952974875862283
        }
      },
      "strategy_metrics_by_strategy": {
        "equal_weight_signals": {
          "hit_rate": {
            "completed_split_count": 37,
            "max": 0.5427077280650784,
            "mean": 0.47896197217843645,
            "min": 0.41798895415095993,
            "std": 0.03270512825187007
          },
          "mean_net_return_per_trade": {
            "completed_split_count": 37,
            "max": 0.0068149943123021976,
            "mean": -0.0007238271169164747,
            "min": -0.007690243676073415,
            "std": 0.0028960889631484124
          }
        },
        "stage1_probability": {
          "hit_rate": {
            "completed_split_count": 37,
            "max": 0.5777777777777777,
            "mean": 0.4695110841178256,
            "min": 0.37777777777777777,
            "std": 0.0511459192120473
          },
          "ic_information_ratio": {
            "completed_split_count": 37,
            "max": 0.4730992578454788,
            "mean": 0.0026480786467443576,
            "min": -0.5161217435748494,
            "std": 0.19260950332054758
          },
          "mean_daily_ndcg_for_top_3": {
            "completed_split_count": 37,
            "max": 0.5924473918298009,
            "mean": 0.49524184033088153,
            "min": 0.3998003760998596,
            "std": 0.03914490913241793
          },
          "mean_daily_net_return_for_top_3": {
            "completed_split_count": 37,
            "max": 0.012478963057421931,
            "mean": -0.002196508693987311,
            "min": -0.016619426338290347,
            "std": 0.0070440133207054206
          },
          "mean_daily_precision_for_top_3": {
            "completed_split_count": 37,
            "max": 0.5777777777777777,
            "mean": 0.4696696696696696,
            "min": 0.3777777777777777,
            "std": 0.051162658429929314
          },
          "mean_daily_spearman_ic": {
            "completed_split_count": 37,
            "max": 0.06658431789554398,
            "mean": 0.001388105868112844,
            "min": -0.058641619343961345,
            "std": 0.0295917829747835
          },
          "mean_net_return_per_trade": {
            "completed_split_count": 37,
            "max": 0.01247896305742193,
            "mean": -0.0022168256869568755,
            "min": -0.01661942633829035,
            "std": 0.0070678451721541535
          },
          "positive_ic_day_rate": {
            "completed_split_count": 37,
            "max": 0.6833333333333333,
            "mean": 0.4983967017865322,
            "min": 0.31666666666666665,
            "std": 0.07629167420461903
          }
        },
        "stage2_ranker": {
          "hit_rate": {
            "completed_split_count": 37,
            "max": 0.6536312849162011,
            "mean": 0.4718161218288204,
            "min": 0.3743016759776536,
            "std": 0.05916328276091602
          },
          "ic_information_ratio": {
            "completed_split_count": 37,
            "max": 0.36461572951359567,
            "mean": -0.03740040853959442,
            "min": -0.3694688876834353,
            "std": 0.17729695981226876
          },
          "mean_daily_ndcg_for_top_3": {
            "completed_split_count": 37,
            "max": 0.6454481276905993,
            "mean": 0.5223427476638431,
            "min": 0.4414763238601053,
            "std": 0.04757272003596457
          },
          "mean_daily_net_return_for_top_3": {
            "completed_split_count": 37,
            "max": 0.023946635836380643,
            "mean": -0.00190055179022776,
            "min": -0.01666589202586474,
            "std": 0.008625771659748878
          },
          "mean_daily_precision_for_top_3": {
            "completed_split_count": 37,
            "max": 0.6555555555555554,
            "mean": 0.4715730497012219,
            "min": 0.375,
            "std": 0.05869485179151583
          },
          "mean_daily_spearman_ic": {
            "completed_split_count": 37,
            "max": 0.12837116089467718,
            "mean": -0.008593551067426776,
            "min": -0.10840986143506622,
            "std": 0.05082579325436991
          },
          "mean_net_return_per_trade": {
            "completed_split_count": 37,
            "max": 0.023966831146606072,
            "mean": -0.0016341576157432541,
            "min": -0.015550882683168014,
            "std": 0.008475766848447698
          },
          "positive_ic_day_rate": {
            "completed_split_count": 37,
            "max": 0.6610169491525424,
            "mean": 0.4862348409591931,
            "min": 0.31666666666666665,
            "std": 0.0792228927815616
          }
        }
      }
    },
    "stage_evidence": {
      "stage1_classifier_gate": {
        "base_positive_label_rate": 0.4760990687948881,
        "brier_score": 0.25183542012766985,
        "gate_survival_rate": 0.522479924156283,
        "log_loss": 0.6970871026634601,
        "passed_trades_avg_return": -0.0002818009996234966,
        "passed_trades_hit_rate": 0.4861531514025638,
        "passed_trades_hit_rate_lift": 0.010054082607675707,
        "passed_trades_recall": 0.5062585809073417,
        "roc_auc": 0.5107693283083687
      },
      "stage2_ranker_allocator": {
        "hit_rate": 0.4718161218288204,
        "ic_information_ratio": -0.03740040853959442,
        "mean_daily_net_return_for_top_k": -0.00190055179022776,
        "mean_daily_precision_for_top_k": 0.4715730497012219,
        "mean_daily_spearman_ic": -0.008593551067426776,
        "mean_net_return_per_trade": -0.0016341576157432541,
        "positive_ic_day_rate": 0.4862348409591931
      }
    },
    "strategies": {
      "equal_weight_signals": {
        "completed_split_count": 37,
        "hit_rate": 0.47896197217843645,
        "mean_net_return_per_trade": -0.0007238271169164747,
        "total_trade_count": 338591
      },
      "stage1_probability": {
        "completed_split_count": 37,
        "hit_rate": 0.4695110841178256,
        "ic_information_ratio": 0.0026480786467443576,
        "mean_daily_ndcg_for_top_3": 0.49524184033088153,
        "mean_daily_ndcg_for_top_6": 0.507413442523313,
        "mean_daily_ndcg_for_top_9": 0.5173840914766488,
        "mean_daily_net_return_for_top_3": -0.002196508693987311,
        "mean_daily_net_return_for_top_6": -0.001230996172656991,
        "mean_daily_net_return_for_top_9": -0.0013503515666320582,
        "mean_daily_precision_for_top_3": 0.4696696696696696,
        "mean_daily_precision_for_top_6": 0.4753303303303303,
        "mean_daily_precision_for_top_9": 0.47665129415129415,
        "mean_daily_spearman_ic": 0.001388105868112844,
        "mean_net_return_per_trade": -0.0022168256869568755,
        "positive_ic_day_rate": 0.4983967017865322,
        "std_daily_net_return_for_top_3": 0.03991739998763833,
        "std_daily_net_return_for_top_6": 0.029682686634924106,
        "std_daily_net_return_for_top_9": 0.025523441594544307,
        "std_daily_spearman_ic": 0.17184570827032455,
        "top_k": 3.0,
        "total_trade_count": 6658
      },
      "stage2_ranker": {
        "completed_split_count": 37,
        "hit_rate": 0.4718161218288204,
        "ic_information_ratio": -0.03740040853959442,
        "mean_daily_ndcg_for_top_3": 0.5223427476638431,
        "mean_daily_ndcg_for_top_6": 0.5494636950302202,
        "mean_daily_ndcg_for_top_9": 0.5730784642677943,
        "mean_daily_net_return_for_top_3": -0.00190055179022776,
        "mean_daily_net_return_for_top_6": -0.001683099431053775,
        "mean_daily_net_return_for_top_9": -0.0015272099760796315,
        "mean_daily_precision_for_top_3": 0.4715730497012219,
        "mean_daily_precision_for_top_6": 0.472465412524973,
        "mean_daily_precision_for_top_9": 0.4724843232508225,
        "mean_daily_spearman_ic": -0.008593551067426776,
        "mean_net_return_per_trade": -0.0016341576157432541,
        "positive_ic_day_rate": 0.4862348409591931,
        "std_daily_net_return_for_top_3": 0.043018778103998345,
        "std_daily_net_return_for_top_6": 0.03452556042576741,
        "std_daily_net_return_for_top_9": 0.030521011027323807,
        "std_daily_spearman_ic": 0.2880822442410155,
        "top_k": 3.0,
        "total_trade_count": 6467
      }
    }
  },
  "models": {
    "files": {
      "stage1_classifier": null,
      "stage2_ranker": null
    },
    "parameters": {
      "stage1_classifier": {},
      "stage2_ranker": {}
    }
  },
  "run": {
    "execution_assumptions": {
      "benchmark_relative": true,
      "classifier_positive_label": "forward 3-bar return exceeded the benchmark",
      "classifier_target": "outperforms_benchmark_3d",
      "forward_return_horizon": 3,
      "label_horizon_bars": 3,
      "outcome_return_column": "forward_relative_return_3d",
      "outcome_return_definition": "forward 3-bar return minus benchmark return (costed)",
      "ranker_target": "forward_relative_return_3d",
      "require_complete_label_horizon": true,
      "slippage_pct": 0.0005,
      "target_mode": "forward_return",
      "transaction_cost_pct": 0.0
    },
    "git_commit": "3aa11b1cee4b07347401b74e7c110b4bea00387e",
    "git_worktree_dirty": false,
    "parameters": {
      "classifier_c_value": 1.0,
      "classifier_class_weight": null,
      "embargo_bars": 15,
      "gate_threshold": 0.48,
      "limit_tickers": null,
      "lookback_years": 10,
      "test_bars": 60,
      "top_k": 3,
      "train_bars": 250
    },
    "run_id": "20260618T235143294627Z",
    "trained_at": "2026-06-18T23:53:23.991303+00:00"
  }
}
